[
    {
        "name": "৩১৬. অগ্রসর হও আজি খ্রীষ্ট সেনা",
        "lyrics": "অগ্রসর হও আজি খ্রীষ্ট-সেনা সব,\nসবে মিলে আইস করি বিজয় রব,\nকর খ্রীষ্টের নামে গৌরব সংঘোষণ,\nদূত ও নরে সবে মিলে কর সষ্কীর্তন!\n\nধূয়াঃ অগ্রসর হও আজি খ্রীষ্ট-সেনা সব,\nসবে মিলে আইস করি বিজয় রব।\n\nপ্রবল সেনা তুল্য খ্রীষ্টের মন্ডলী;\nত্রাতার পদ-চিহ্নে সকরে চলি;\nকেহ পৃথক নহি একাঙ্গ সকল,\nএকই আশা, একই সত্য, একই প্রেম সম্বল।\n\nরাজ্য সম্রাট কিরীট কত আসে যায়,\nখ্রীষ্টের মন্ডলী চির বৃদ্ধি পায়,\nনরক দ্বার না পারে পরাজিতে তায়,\nখ্রীষ্টের এ প্রতিজ্ঞা দেখ মানে না বাধায়।\n\n- যাকোব কান্তিনাথ বিশ্বাস"
    },
    {
        "name": "৯৯. অদ্য যীশু উঠিলেন",
        "lyrics": "অদ্য যীশু উঠিলেন, হাল্লিলুয়া!\nইহা কেমন শুভ দিন, হাল্লিলুয়া!\nখ্রীষ্টের আত্ম-বলিদান, হাল্লিলুয়া!\nসাধে মোদের পরিত্রাণ, হাল্লিলুয়া!\n\nআইস আমরা হৃষ্ট হই, হাল্লিলুয়া!\nস্বর্গ রাজ্যের কীর্তি গাই, হাল্লিলুয়া!\nক্রুশে যিনি মরিলেন, হাল্লিলুয়া!\nতিনি নিত্য জীবন দেন, হাল্লিলুয়া!\n\nআহ্লাদ কর ভক্তগণ, হাল্লিলুয়া!\nখ্রীষ্টের নামে সর্বক্ষণ, হাল্লিলুয়া!\nমৃত্যুচ্ছায়া হইল নাশ, হাল্লিলুয়া!\nজীবন-দীপ্তি পায় প্রকাশ, হাল্লিলুয়া!\n\nআমরা যেন সর্বদাই, হাল্লিলুয়া!\nযীশুর অনুগামী রই, হাল্লিলুয়া!\nশেষে মৃত্যু করে জয়, হাল্লিলুয়া!\nহইয়া উঠি তেজোয়ময়, হাল্লিলুয়া!\n\n- জন্ জেমস উইটব্রেট"
    },
    {
        "name": "২৮১. অন্তর হইতে অন্তর হইও না",
        "lyrics": "গীত ৫১:১১\nখাম্বাজ--জৎ\n\nঅন্তর হইতে অন্তর হইও না।\n\n১।\nআমি যে পামর, পাপ মন মোর,\nহে পরমেশ্বর, করহ করুণা।\n\n২।\nআমি অতি ক্ষুদ্র, দুঃখিত দরিদ্র,\nযীশু নামে সম্পদ, মম সম্ভাবনা।\n\n৩।\nযীশু-প্রেম-ধন, কর বিতরণ,\nঐহিক সম্পদ, সম্ভ্রম চাহি না।\n\n৪।\nসমূহ পরীক্ষা, আনিছে আশঙ্কা\nপ্রভু কর রক্ষা, বিলম্ব করো না।\n\n৫।\nক্ষম অপরাধ, দেহ আশীর্বাদ,\nযীশু খ্রীষ্টের গুণে, কর হে মার্জনা।\n\n-তারাচাঁদ দত্ত"
    },
    {
        "name": "১৫৯. অপার জ্ঞানের উৎস বচন তোমার",
        "lyrics": "গীত ১১৯:১০৫\nবিহঙ্গড়া-চৌতাল\n\nঅপার জ্ঞানের উৎস বচন তোমার,\nআহা, কিবা দিব্য সত্যের আধার!\nএই জ্ঞান-ভাস্করে সততা দান করে\nসত্য দীপ্তি অন্তরে, অজ্ঞতা-তম হরে\nঅন্ধ সবাকার।\n\n১।\nচরণে দীপ্তিদায়ী আঁধার ভবে;\nদুঃখে সান্ত্বনা করে দুঃখিত সবে,\nমহামূল্য রতন নয়নের অঞ্জন,\nদীনহীনের ধন; সতত স্মরে মন\nবচন তোমার।\n\n২।\nহে নাথ, তব বাণী যে রাখে মনে,\nসঙ্কটে বিপদে সে সুখী ভুবনে,\nনাহি ডরে শত্রুরে এ ভীষণ সংসারে,\nসাদা শান্তি অন্তরে, নয়ন সদা হেরে\nবদন তোমার।\n\n৩।\nহে নাথ, তব বাণী যে রাখে মনে,\nসান্ত্বনা পাইব সর্বদা জীবনে;\nনা হই যেন বিস্মৃত ঐ মহামূল্য ধনে,\nপবিত্র আত্মাদানে পূর্ণ কর এক্ষণে\nহৃদয় আমার।\n\n-যাকোব কান্তিনাথ বিশ্বাস"
    },
    {
        "name": "৪২. অপার মহিমা তব নাহিক",
        "lyrics": "রোমীয় ৮:৩২\nআলেয়া – একতালা\n\nঅপার মহিমা তব, নাহিক হে তুলনা,\nঅতুল তোমার প্রেম, কে করে হে বর্ণনা।\n\n১।\nতুমি নিজ পুত্র দিলে, তারিতে পাতকিদলে,\nদিয়াছ সকলি প্রভু, করিয়া ত করুণা।\n\n২।\nশোক-দুঃখে অভিভূত, ছিলাম যখন পিতঃ,\nতোমারই প্রেম-বাহুতে, করেছ হে সান্ত্বনা।\n\n৩।\nতোমার শ্রীমুখ-জ্যোতি, দেখিয়াছি দিবারাতি,\nরক্ষিয়াছ নাথ তুমি, হ’তে বিপদ যন্ত্রণা।\n\n৪।\nযাগ-যজ্ঞে নহ প্রীত, তব যজ্ঞ চূর্ণ চিত,\nলহ আজি তাহা পিতঃ পূর্ণ কর কামনা।\n\n-তিনকড়ি চট্রোপাধ্যায়"
    },
    {
        "name": "৭১. অপূর্ব প্রেমে প্রভু এ জগৎ মাতাল",
        "lyrics": "২ করি ৫: ১৪\nসংকীর্তন - একতালা\n\nঅপূর্ব প্রেমে প্রভু এ জগৎ মাতালে,\nতুমি প্রেম-বলে, ধরাতলে বিজয়ী হইলে।\n\n১।\nতুমি প্রেম ক’রে\n(যীশু হে, ও আমার দয়াল যীশু)\nতুমি প্রেম ক’রে নরের তরে, এ ভবে আইলে।\n\n২।\nতুমি ভবে এসে, (যীশু হে, ও আমার দয়াল যীশু)\nতুমি ভবে এসে, কত ক্লেশে, জীবন যাপিলে।\n\n৩।\nতুমি পাপীর তরে, (যীশু হে, ও আমার দয়াল যীশু)\nতুমি পাপীর তরে, ক্রুশোপরে, মরণ ভুগিলে।\n\n৪।\nআমার প্রেম-তরি,(যীশু হে, ও আমার দয়াল যীশু)\nতুমি প্রেম তরি প্রেম করি, পাপী পার করিলে।\n\n৫।\nআমার প্রেম-রতন, (যীশু হে, ও আমার দয়াল যীশু)\nতুমি প্রেম-রতন, তোমায় যতন, করব সর্বকালে।\n\n৬।\nতোমার প্রেম-রসে, (যীশু হে, ও আমার দয়াল যীশু)\nতোমার প্রেম-রসে, সর্ব দেশে, মাতাও সকলে।\n\n-রামচরণ ঘোষ"
    },
    {
        "name": "৪১৯. অক্ষয় আনন্দধামে চল রে",
        "lyrics": "অক্ষয় আনন্দধামে, চল রে পথিক মন;\nপাইবে শাশ্বত সুখ, জুড়াবে দগ্ধ জীবন!\nসে বড় পবিত্র দেশ, নাহি পাপ তাপ লেশ,\nপ্রেমানন্দের সমাবেশ, সকল শোকভঞ্জন।\n(তথা) শান্তি নামে পুণ্য নাদী, বহিতেছে নিরবধি,\nরবে না মনের ব্যাধি, করিলে অবগাহন;\nঅজস্র অমিয় সুধা, বাঞ্ছা পুরে পাবে সদা,\nঘুঁচিবে আত্মার ক্ষুধা, সে সুধা করি সেবন।\n\n-অজ্ঞাত"
    },
    {
        "name": "৪২০. অবনত হয়ে প্রভু প্রণতি তোমায়",
        "lyrics": "অবনত হয়ে প্রভু প্রণমি তোমায়,\nপ্রণমি তোমায় প্রভু প্রণমি তোমায়।\nঅবনত হয়ে...。\n\n১।\nতুমি প্রভু যীশু বড় দয়াময়\nতোমা বিনা নাই মোর কোন যে উপায়;\nপ্রণমি তোমায় প্রভু, প্রণমি তোমায়।\n\n২।\nমোরে দয়া কর আজি এ সময়,\nমম জীবন ধন্য হোক তোমার ছোঁয়ায়,\nহৃদয় বীণার তারে বাজুক সদাই,\nজয় যীশু, জয় যীশু, জয় যীশু জয়।\n\n-দেবী প্রসাদ রায় চৌধুরী"
    },
    {
        "name": "৪২১. অমরাবতীর রাজপুরী হতে এলো",
        "lyrics": "অমরাবতীর রাজপুরী হতে\nএলো আজি এলো মহীয়ান;\nহে পৃথিবী শোনা, তাহারি লাগিয়া\nগাহে তব বন্দনা গান।\n\nরাজার কুমার এসেছে একা, পান্থনিবাসে মিলিবে দেখা;\nএসো একবার হের গো তাঁরে, সার্থক হবে তব প্রাণ।\n\nবন্ধু মোদের চাহিয়া দেখো, আঁধার গিয়াছে চলে;\nদিব্যলোকের আশীষ ঝরে, কনক উদয়াচলে।\n\nসেই আলোকের পুণ্য শিখায়, তামসী ব্যথা নিমিষে মিলায়;\nবিশ্ববীণায় ধ্বনিয়া ওঠে, নবজীবনের জয়গান।\n\n- নির্মল পান্ডে"
    },
    {
        "name": "৩৩৭. আঘাত করেন উনি কে",
        "lyrics": "১।\nআঘাত করেন, উনি কে-\nদিব্য পুরুষ বাহিরে?\nউনি পথিক, রাজার মত,\nকভু এমন দেখি নাই;\nতাঁহার জন্য হৃদি ভবন,\nখুলে দিবে নাকি, ভাই?\n\n২।\nঐ যে দেখ, যতনে\nআঘাত করেন সঘনে;\nমন কি তব বদ্ধ রবে?\nকরিবে না পরিস্কার?\nদিবে নাকি তাঁকে তব\nহৃদয় রাজ্যের অধিকার?\n\n৩।\nদারুণ ক্ষতযুক্ত হাত\nদ্বারে করিছে আঘাত\nপাপীর, উনি মুক্তিদাতা,\nsর্ব সুখের মূলাধার;\nচির শান্তি চাহ যদি,\nশীঘ্র খোল হৃদয় দ্বার。\n\n- খ্রীষ্ট সঙ্গীত"
    },
    {
        "name": "২৭৮. আজ তুমি আমার সঙ্গে",
        "lyrics": "লূক ২৩:৪৩\nবেলোখালী--একতালা\n\nআজ তুমি আমার সঙ্গে স্বর্গধামে চলে যাবে,\nআর এ যাতনা কখনো হবে না,\nসুমিষ্ট সান্ত্বনা তথায় পারে।\n\n১।\nআমার পদচিহ্নে পদ দিয়ে দিয়ে,\nপিছে পিছে তুমি এসো গো ধেয়ে,\nমৃত্যুর হুঙ্কারে, কেঁপো না অন্তরে,\nঅমৃত নগরে এখনি যাবে。\n\n২।\nযত পাপী তাপী এস ক্রুশের কাছে,\nঅনুতাপে ক্ষমা প্রস্তুত আছে,\nযাগ-যজ্ঞ নিত্য, কিংবা প্রায়শ্চিত্ত ,\nsকলি অনিত্য দেখতে পাবে。\n\n৩।\nওহে ক্রুশ, সমাধি, পুনরুত্থান,\nগৌরবে বেষ্টিত স্বর্গারোহণ,\nএমন সুন্দর সুগম্য সোপান,\nবিশ্বাস নয়নে দেখতে পাবে。\n\n- বিজয় নাথ সরকার"
    },
    {
        "name": "১০১. আজ মহা পরিত্রাণ ভাই",
        "lyrics": "আজ মহা পরিত্রাণ ভাই আজ মহা পরিত্রাণ\nযীশু উঠেছেন দেখ পাপীরে করিতে ত্রাণ।\n\n১।\nচেয়ে দেখ কবর পানে যীশুর দেহ নাই সেখানে,\n(শুধু) বস্ত্রগুলি পড়ে আছে দূতে করে সাক্ষ্যদান。\n\n২।\nবিশ্বাসী যদিও মরে, তবু সে উঠিবে পরে,\n(ও ভাই) মৃত্যুঞ্জয়ী যীশু সেই সত্যের চির প্রমাণ。\n\n৩।\nযীশু আগে স্বর্গে গিয়ে, স্বর্গ দুয়ার দিলেন খুলে,\n(আমরা) যাব যাব স্বর্গে যাব যীশু-রক্তে পেয়ে ত্রাণ。\n\n৪।\nনেচে নেচে তালে তালে, সবে মিলে বাহু তুলে;\n(এখন) জয় যীশু জয় যীশু বলে কর তাঁহার গুণকীর্তন。\n\n- ইউসুফ বিশ্বাস"
    },
    {
        "name": "৫৭. আজ শুভ বড়দিন ভাই",
        "lyrics": "যোহন ১:১৪\nবসন্ত - একতালা\n\nআজ শুভ বড়দিন ভাই, আজ শুভ বড়দিন,\nখ্রীষ্ট যীশু এলেন ভবে, ছেড়ে স্বর্গের সিংহাসন。\n\n১।\nচেয়ে দেখ বৈৎলেহমে, গোয়াল ঘরে, মেরীর কোলে,\nযাবপাত্রে আছেন শুয়ে, পাপীদের মুক্তির কারণ。\n\n২।\nস্বর্গদূত নেচে নেচে, সংবাদ দিল রাখালগণে,\nতারা দেখে পন্ডিতগণে, আসে করিতে দর্শন。\n\n৩।\nপাপের সকল দন্ড-নিতে, এলেন যীশু অবনীতে,\nযীশুর রক্তে ধৌত হয়ে, কর তাঁহার নাম কীর্তন。\n\n৪।\nধন্য যীশু বল সবে, মহোল্লাসে উচ্চরবে,\nহাল্লেলূয়া স্তবে সবে পূর্ণ কর ত্রিভুবন。\n\n- সুনীল কুমার সরকার"
    },
    {
        "name": "১. আজি এলেম প্রভু তোমার",
        "lyrics": "ফাফি- ছেপকা (জৎ)\nগীত 27:4; লেবীয় 25:21\n\nআজী এলেম প্রভু, তোমার ঘরে করিতে ভজন;\nদীনহীনে দয়া কর, করি নিবেদন。\n\n১।\nতব গৃহে যারা যায়, অবশ্য সান্ত্বনা পায়,\nনিরলস হ’য়ে যেন, করয়ে সাধন。\n\n২।\nতব স্থান কেমন মান্য, যেই যায় সেই ধন্য,\nহয় তারা মহামান্য, পেয়ে খ্রীষ্ট-ধন。\n\n৩।\nতোমার কথা যখন শুনে, ভাবে তখন মনে মনে,\nপ্রভু আছেন এই স্থানে, শাস্ত্রের বচন。\n\n৪।\nবৃষ্টি দ্বারা মরুভূমি, যেমন আর্দ্র কর তুমি,\nতেমনি কর হে স্বামী, ভক্তদের মন。\n\n৫।\nআমারা অতি দুরাচার, উপায় নাহিক আর,\nকৃপা করি গ্রাহ্য কর, পাতকি-জীবন。\n\n- (অজ্ঞাত)"
    },
    {
        "name": "১৪৫. আত্মন এস মোদের অন্তরে",
        "lyrics": "রোমীয় ১৫:১৬\nগৌর সারঙ্গ : একতালা\n\nআত্মন এস মোদের অন্তরে,\nউজ্জ্বল কর আপনার করে。\n\n১।\nতোমার সত্যের আলো প্রদান করে,\nসুপথ দেখাও অন্তরে। (ওহে সত্যের আলো)\n\n২।\nবহাও জীবন-বায়ু শক্তি-ভরে,\nসবল কর অন্তরে। (ওহে জীবন-বায়ু)\n\n৩।\nঅগ্নি স্পর্শ দিয়া ওষ্ঠাধরে,\nখাঁটি কর অন্তরে। (ওহে স্বর্গের আগুন)\n\n৪।\nসেই কপোত বেশে নেমে ধীরে,\nনিবাস কর অন্তরে। (ওহে আত্মা কপোত)\n\n৫।\nমোদের যীশু-লতার শাখা করে,\nদেও তাঁরি রস অন্তরে। (ওহে শক্তিদাতা)\n\n৬।\nশিখাও ’আব্বা’ বলা আমাদের,\nদেও পুত্রের ভাব অন্তরে। (ওহে সত্য গুরু)\n\n৭।\nদেখাও যীশুর মূর্তি অঙ্কিত করে,\nস্পষ্ট মোদের অন্তরে। (ওহে যীশুর আত্মা)\n\n৮।\nদুঃখিত হ’য়ে যেও না হে ফিরে,\nসদা থাক অন্তরে। (ওহে ভক্ত সখা)\n\n- ডবলু, কেরী"
    },
    {
        "name": "১৪৬. আত্মন এস হৃদয় উদ্যানে",
        "lyrics": "পরমগীত ৪:১৬\nলুম ঝিঁঝিট - একতালা\n\nআত্মন ! এস হৃদয় উদ্যানে\nতুষিব হৃদয় দানে।\n\n১।\nযেমত বায়ু বিহনে, জীবাদি বাঁচে না প্রাণে,\nসেই মত তোমা বিনে, বাঁচি না এ জীবনে。\n\n২।\nযেমন বায়ু সুখী করে, তেমন সুখী কর মোরে,\nসদাই স্নিগ্ধ অন্তরে, ডাকব তোমায় এক প্রাণে。\n\n৩।\nওহে প্রভু দয়াময়, উদ্যানে এস এ সময়,\nনানা জাতি পুস্পচয়, ফুটাও হৃদয়-কাননে。\n\n৪।\nবিশ্বাস ভক্তি পবিত্রতা, প্রেম-আনন্দ-সহিষ্ণুতা,\nমধুর ভাব দয়া নম্রতা, চাই এই উদ্যানে。\n\n- প্রভাত চন্দ্র দাস"
    }
]
